graylog_telemidia/__init__.py
graylog_telemidia/main.py
graylog_telemidia-1.0.14.dist-info/METADATA
graylog_telemidia-1.0.14.dist-info/WHEEL
graylog_telemidia-1.0.14.dist-info/top_level.txt
graylog_telemidia-1.0.14.dist-info/RECORD
