Metadata-Version: 2.1
Name: graylog-telemidia
Version: 1.0.14
Summary: Este pacote fornece uma interface simples e eficiente para enviar mensagens de log para o Graylog, seguindo o padrão utilizado pela Telemidia.
Home-page: https://github.com/telemidia-isp/graylog-telemidia-py
Author: Thales Casa Grande de Lima
Author-email: cor@telemidia.net.br
License: UNKNOWN
Platform: UNKNOWN
Classifier: Programming Language :: Python :: 3
Classifier: License :: OSI Approved :: MIT License
Classifier: Operating System :: OS Independent
Requires-Python: >=3.6
Requires-Dist: graypy
